target_mako/__init__.py
target_mako/dict_proxy.py
target_mako/formatting_functions.py
tests/__init__.py
tests/formatting_functions.py
tests/test_dict_proxy.py
target_mako-1.3.0.dist-info/LICENSE
target_mako-1.3.0.dist-info/METADATA
target_mako-1.3.0.dist-info/WHEEL
target_mako-1.3.0.dist-info/entry_points.txt
target_mako-1.3.0.dist-info/top_level.txt
target_mako-1.3.0.dist-info/RECORD
