Metadata-Version: 2.1
Name: target-mako
Version: 1.3.0
Summary: Singer.io target for extracting data
Home-page: https://github.com/ericlebail/target-mako
Author: elebail
Classifier: Programming Language :: Python :: 3 :: Only
Classifier: License :: OSI Approved :: GNU Affero General Public License v3
Classifier: Operating System :: OS Independent
License-File: LICENSE
Requires-Dist: singer-python (==5.13.0)
Requires-Dist: jsonschema (==2.6.0)
Requires-Dist: Mako (==1.2.4)
Provides-Extra: test
Requires-Dist: pytest (==7.2.0) ; extra == 'test'
Requires-Dist: pytest-cov (==4.0.0) ; extra == 'test'
Requires-Dist: pytest-mock (==3.10.0) ; extra == 'test'
Requires-Dist: testfixtures (==7.0.4) ; extra == 'test'
Requires-Dist: coverage (==7.0.1) ; extra == 'test'
